{
  "scenario_file": "D:\\Codex_Project\\bs_1.0_4.22\\results\\stage1\\normal\\normal_scenario_weighted.json",
  "stage1_method": "grasp_multi_start",
  "seed": 7,
  "grasp_seed": 7,
  "iterations": [
    10,
    30,
    50
  ],
  "rcl_ratios": [
    0.05,
    0.1,
    0.2
  ],
  "rows": [
    {
      "scenario_file": "D:\\Codex_Project\\bs_1.0_4.22\\results\\stage1\\normal\\normal_scenario_weighted.json",
      "stage1_method": "grasp_multi_start",
      "grasp_iterations": 10,
      "grasp_rcl_ratio": 0.05,
      "grasp_seed": 7,
      "fr": 1.0,
      "mean_completion_ratio": 1.0,
      "window_count": 12,
      "activation_count": 24,
      "avg_hot_coverage": 0.90049930992415,
      "eta_cap": 0.0165236320552432,
      "runtime_seconds": 109.01902100000007,
      "wall_clock_seconds": 111.39104170000064,
      "timed_out": false,
      "result_file": "D:\\Codex_Project\\bs_1.0_4.22\\results\\stage1\\grasp_sensitivity\\normal_grasp_it10_rcl0p05_result.json"
    },
    {
      "scenario_file": "D:\\Codex_Project\\bs_1.0_4.22\\results\\stage1\\normal\\normal_scenario_weighted.json",
      "stage1_method": "grasp_multi_start",
      "grasp_iterations": 10,
      "grasp_rcl_ratio": 0.1,
      "grasp_seed": 7,
      "fr": 1.0,
      "mean_completion_ratio": 1.0,
      "window_count": 12,
      "activation_count": 24,
      "avg_hot_coverage": 0.846322846683893,
      "eta_cap": 0.012463944893655179,
      "runtime_seconds": 121.80506890000106,
      "wall_clock_seconds": 124.43484519999765,
      "timed_out": false,
      "result_file": "D:\\Codex_Project\\bs_1.0_4.22\\results\\stage1\\grasp_sensitivity\\normal_grasp_it10_rcl0p10_result.json"
    },
    {
      "scenario_file": "D:\\Codex_Project\\bs_1.0_4.22\\results\\stage1\\normal\\normal_scenario_weighted.json",
      "stage1_method": "grasp_multi_start",
      "grasp_iterations": 10,
      "grasp_rcl_ratio": 0.2,
      "grasp_seed": 7,
      "fr": 1.0,
      "mean_completion_ratio": 1.0,
      "window_count": 12,
      "activation_count": 24,
      "avg_hot_coverage": 0.8144932601205858,
      "eta_cap": 0.018327747800167604,
      "runtime_seconds": 88.06864240000141,
      "wall_clock_seconds": 90.83186489999935,
      "timed_out": false,
      "result_file": "D:\\Codex_Project\\bs_1.0_4.22\\results\\stage1\\grasp_sensitivity\\normal_grasp_it10_rcl0p20_result.json"
    },
    {
      "scenario_file": "D:\\Codex_Project\\bs_1.0_4.22\\results\\stage1\\normal\\normal_scenario_weighted.json",
      "stage1_method": "grasp_multi_start",
      "grasp_iterations": 30,
      "grasp_rcl_ratio": 0.05,
      "grasp_seed": 7,
      "fr": 1.0,
      "mean_completion_ratio": 1.0,
      "window_count": 12,
      "activation_count": 24,
      "avg_hot_coverage": 0.8656946146879865,
      "eta_cap": 0.006219823250228314,
      "runtime_seconds": 306.4122600000046,
      "wall_clock_seconds": 309.1992981999938,
      "timed_out": false,
      "result_file": "D:\\Codex_Project\\bs_1.0_4.22\\results\\stage1\\grasp_sensitivity\\normal_grasp_it30_rcl0p05_result.json"
    },
    {
      "scenario_file": "D:\\Codex_Project\\bs_1.0_4.22\\results\\stage1\\normal\\normal_scenario_weighted.json",
      "stage1_method": "grasp_multi_start",
      "grasp_iterations": 30,
      "grasp_rcl_ratio": 0.1,
      "grasp_seed": 7,
      "fr": 1.0,
      "mean_completion_ratio": 1.0,
      "window_count": 12,
      "activation_count": 24,
      "avg_hot_coverage": 0.8646192800574818,
      "eta_cap": 0.008672106533284905,
      "runtime_seconds": 267.9138246000002,
      "wall_clock_seconds": 270.76407689999905,
      "timed_out": false,
      "result_file": "D:\\Codex_Project\\bs_1.0_4.22\\results\\stage1\\grasp_sensitivity\\normal_grasp_it30_rcl0p10_result.json"
    },
    {
      "scenario_file": "D:\\Codex_Project\\bs_1.0_4.22\\results\\stage1\\normal\\normal_scenario_weighted.json",
      "stage1_method": "grasp_multi_start",
      "grasp_iterations": 30,
      "grasp_rcl_ratio": 0.2,
      "grasp_seed": 7,
      "fr": 1.0,
      "mean_completion_ratio": 1.0,
      "window_count": 12,
      "activation_count": 24,
      "avg_hot_coverage": 0.8111386957658172,
      "eta_cap": 0.009872160605669906,
      "runtime_seconds": 283.0423097000021,
      "wall_clock_seconds": 285.8089899999977,
      "timed_out": false,
      "result_file": "D:\\Codex_Project\\bs_1.0_4.22\\results\\stage1\\grasp_sensitivity\\normal_grasp_it30_rcl0p20_result.json"
    },
    {
      "scenario_file": "D:\\Codex_Project\\bs_1.0_4.22\\results\\stage1\\normal\\normal_scenario_weighted.json",
      "stage1_method": "grasp_multi_start",
      "grasp_iterations": 50,
      "grasp_rcl_ratio": 0.05,
      "grasp_seed": 7,
      "fr": 1.0,
      "mean_completion_ratio": 1.0,
      "window_count": 12,
      "activation_count": 24,
      "avg_hot_coverage": 0.8656946146879865,
      "eta_cap": 0.006219823250228314,
      "runtime_seconds": 487.15954700000293,
      "wall_clock_seconds": 489.8013155000008,
      "timed_out": false,
      "result_file": "D:\\Codex_Project\\bs_1.0_4.22\\results\\stage1\\grasp_sensitivity\\normal_grasp_it50_rcl0p05_result.json"
    },
    {
      "scenario_file": "D:\\Codex_Project\\bs_1.0_4.22\\results\\stage1\\normal\\normal_scenario_weighted.json",
      "stage1_method": "grasp_multi_start",
      "grasp_iterations": 50,
      "grasp_rcl_ratio": 0.1,
      "grasp_seed": 7,
      "fr": 1.0,
      "mean_completion_ratio": 1.0,
      "window_count": 12,
      "activation_count": 24,
      "avg_hot_coverage": 0.9249095894343957,
      "eta_cap": 0.0,
      "runtime_seconds": 459.5430128000007,
      "wall_clock_seconds": 462.4055825000032,
      "timed_out": false,
      "result_file": "D:\\Codex_Project\\bs_1.0_4.22\\results\\stage1\\grasp_sensitivity\\normal_grasp_it50_rcl0p10_result.json"
    },
    {
      "scenario_file": "D:\\Codex_Project\\bs_1.0_4.22\\results\\stage1\\normal\\normal_scenario_weighted.json",
      "stage1_method": "grasp_multi_start",
      "grasp_iterations": 50,
      "grasp_rcl_ratio": 0.2,
      "grasp_seed": 7,
      "fr": 1.0,
      "mean_completion_ratio": 1.0,
      "window_count": 12,
      "activation_count": 24,
      "avg_hot_coverage": 0.8567554191788689,
      "eta_cap": 0.0003527510921355648,
      "runtime_seconds": 422.26529600000504,
      "wall_clock_seconds": 425.02549259999796,
      "timed_out": false,
      "result_file": "D:\\Codex_Project\\bs_1.0_4.22\\results\\stage1\\grasp_sensitivity\\normal_grasp_it50_rcl0p20_result.json"
    }
  ]
}